hardware_code/__init__.py
hardware_code/harvard_pumps.py
hardware_code/neslab_circulator_bath.py
hardware_code/teledyne_pumps.py
chembot-0.0.1.dist-info/LICENSE.txt
chembot-0.0.1.dist-info/METADATA
chembot-0.0.1.dist-info/WHEEL
chembot-0.0.1.dist-info/top_level.txt
chembot-0.0.1.dist-info/RECORD
