Metadata-Version: 2.1
Name: chembot
Version: 0.0.1
Summary: ChemBot: Tools for automating chemistry.
Home-page: UNKNOWN
Author: Dylan Walsh
Author-email: dylanwal@mit.edu
License: MIT License
Platform: UNKNOWN
Classifier: Programming Language :: Python :: 3
Classifier: License :: OSI Approved :: MIT License
Classifier: Operating System :: OS Independent
License-File: LICENSE.txt
